setup.py
jianhong/__init__.py
jianhong/logger.py
jianhong.egg-info/PKG-INFO
jianhong.egg-info/SOURCES.txt
jianhong.egg-info/dependency_links.txt
jianhong.egg-info/not-zip-safe
jianhong.egg-info/top_level.txt