Metadata-Version: 1.1
Name: jianhong
Version: 1.0.1
Summary: jianhong's develop tools
Home-page: https://github.com/chenjianhong/jianhong
Author: chen jianhong
Author-email: 1815515831@qq.com
License: BSD
Platform: UNKNOWN
Classifier: Development Status :: 3 - Alpha
Classifier: Environment :: Web Environment
Classifier: Intended Audience :: Developers
Classifier: License :: OSI Approved :: BSD License
Classifier: Operating System :: OS Independent
Classifier: Programming Language :: Python
Classifier: Framework :: Django
